moroccan_atlas/personal/__init__.py
moroccan_atlas/personal/constants.py
moroccan_atlas/personal/main.py
moroccan_atlas/personal/utils.py
moroccan_atlas-0.1.3.dist-info/LICENSE
moroccan_atlas-0.1.3.dist-info/METADATA
moroccan_atlas-0.1.3.dist-info/WHEEL
moroccan_atlas-0.1.3.dist-info/RECORD
