Metadata-Version: 2.3
Name: moroccan_atlas
Version: 0.1.3
Summary: A Python toolbox of validators, parsers, and datasets for Moroccan-specific data formats and regions.
License: See LICENSE
Author: TAnas0
Author-email: anastiour@gmail.com
Requires-Python: >=3.10
Classifier: License :: Other/Proprietary License
Classifier: Programming Language :: Python :: 3
Classifier: Programming Language :: Python :: 3.10
Classifier: Programming Language :: Python :: 3.11
Classifier: Programming Language :: Python :: 3.12
Classifier: Programming Language :: Python :: 3.13
Provides-Extra: dev
Requires-Dist: black ; extra == "dev"
Requires-Dist: pytest ; extra == "dev"
Project-URL: Homepage, https://github.com/TAnas0/moroccan-atlas
Project-URL: Issue Tracker, https://github.com/TAnas0/moroccan-atlas/issues
